mhm/__init__.py
mhm/_version.py
mhm/cli.py
mhm/download.py
mhm/tools.py
mhm/wrapper.cpython-311-aarch64-linux-gnu.so
mhm.libs/libgfortran-8a9a71bc.so.5.0.0
mhm.libs/libhdf5-2559098b.so.200.2.0
mhm.libs/libhdf5_hl-c35d1004.so.200.1.0
mhm.libs/libnetcdf-68aa264a.so.19.1.0
mhm.libs/libnetcdff-f1b7add8.so.7.1.0
mhm-5.13.2.dist-info/METADATA
mhm-5.13.2.dist-info/WHEEL
mhm-5.13.2.dist-info/entry_points.txt
mhm-5.13.2.dist-info/RECORD
mhm-5.13.2.dist-info/licenses/AUTHORS
mhm-5.13.2.dist-info/licenses/COPYING
mhm-5.13.2.dist-info/licenses/COPYING.LESSER
mhm-5.13.2.dist-info/licenses/LICENSE.md
