Metadata-Version: 2.2
Name: mhm
Version: 5.13.2
Summary: Python distribution of mHM with bindings.
Keywords: mHM
Author-Email: mHM Developers <mhm-admin@ufz.de>
License: LGPL-3.0
Classifier: Development Status :: 3 - Alpha
Classifier: Intended Audience :: Developers
Classifier: Intended Audience :: End Users/Desktop
Classifier: Intended Audience :: Science/Research
Classifier: Intended Audience :: Education
Classifier: License :: OSI Approved :: GNU Lesser General Public License v3 (LGPLv3)
Classifier: Natural Language :: English
Classifier: Operating System :: Unix
Classifier: Operating System :: MacOS
Classifier: Programming Language :: Python
Classifier: Programming Language :: Python :: 3
Classifier: Programming Language :: Python :: 3 :: Only
Classifier: Programming Language :: Python :: 3.9
Classifier: Programming Language :: Python :: 3.10
Classifier: Programming Language :: Python :: 3.11
Classifier: Programming Language :: Python :: 3.12
Classifier: Programming Language :: Python :: 3.13
Classifier: Programming Language :: Python :: 3.14
Classifier: Topic :: Scientific/Engineering
Classifier: Topic :: Scientific/Engineering :: Hydrology
Classifier: Topic :: Scientific/Engineering :: Mathematics
Classifier: Topic :: Scientific/Engineering :: Physics
Classifier: Topic :: Utilities
Project-URL: Changelog, https://www.mhm-ufz.org
Project-URL: Conda-Forge, https://anaconda.org/conda-forge/mhm
Project-URL: Documentation, https://www.mhm-ufz.org
Project-URL: Homepage, https://www.mhm-ufz.org
Project-URL: Source, https://www.mhm-ufz.org
Project-URL: Tracker, https://www.mhm-ufz.org
Requires-Python: >=3.9
Requires-Dist: numpy>=1.17.3
Provides-Extra: test
Requires-Dist: pytest-cov>=3; extra == "test"
Requires-Dist: xarray; extra == "test"
Requires-Dist: netCDF4; extra == "test"
